compressed_file_iterator/__init__.py
compressed_file_iterator/compressed_file_iterator.py
compressed_file_iterator-0.0.1.dist-info/LICENSE
compressed_file_iterator-0.0.1.dist-info/METADATA
compressed_file_iterator-0.0.1.dist-info/WHEEL
compressed_file_iterator-0.0.1.dist-info/top_level.txt
compressed_file_iterator-0.0.1.dist-info/RECORD
