Metadata-Version: 2.1
Name: compressed-file-iterator
Version: 0.0.1
Summary: Configurable iterator-based access to compressed files.
Home-page: https://github.com/atcroft/compressed_file_iterator
Author: Albert Croft
Project-URL: Bug Reports, https://github.com/atcroft/compressed_file_iterator/issues
Project-URL: Source, https://github.com/atcroft/compressed_file_iterator/
Keywords: iterator,archived,compressed
Classifier: Development Status :: 3 - Alpha
Classifier: License :: OSI Approved :: BSD License
Classifier: Programming Language :: Python :: 3
Classifier: Programming Language :: Python :: 3.5
Classifier: Programming Language :: Python :: 3.6
Classifier: Programming Language :: Python :: 3.7
Classifier: Programming Language :: Python :: 3.8
Classifier: Programming Language :: Python :: 3.9
Classifier: Programming Language :: Python :: 3.10
Classifier: Operating System :: OS Independent
Classifier: Topic :: System :: Archiving
Classifier: Topic :: Text Processing :: Filters
Requires-Python: >=3
License-File: LICENSE
